{"primaryContentSections":[{"kind":"declarations","declarations":[{"tokens":[{"kind":"keyword","text":"struct"},{"kind":"text","text":" "},{"kind":"identifier","text":"DateRef"}],"languages":["swift"],"platforms":["macOS"]}]},{"kind":"content","content":[{"anchor":"overview","level":2,"type":"heading","text":"Overview"},{"type":"paragraph","inlineContent":[{"type":"text","text":"The "},{"type":"codeVoice","code":"GDate"},{"type":"text","text":" data structure represents a day between January 1, Year 1,"},{"type":"text","text":" "},{"type":"text","text":"and sometime a few thousand years in the future (right now it will go"},{"type":"text","text":" "},{"type":"text","text":"to the year 65535 or so, but [method"},{"type":"codeVoice","code":"GLib.Date.set_parse"},{"type":"text","text":"] only parses up to the"},{"type":"text","text":" "},{"type":"text","text":"year 8000 or so - just count on “a few thousand”). "},{"type":"codeVoice","code":"GDate"},{"type":"text","text":" is meant to"},{"type":"text","text":" "},{"type":"text","text":"represent everyday dates, not astronomical dates or historical dates"},{"type":"text","text":" "},{"type":"text","text":"or ISO timestamps or the like. It extrapolates the current Gregorian"},{"type":"text","text":" "},{"type":"text","text":"calendar forward and backward in time; there is no attempt to change"},{"type":"text","text":" "},{"type":"text","text":"the calendar to match time periods or locations. "},{"type":"codeVoice","code":"GDate"},{"type":"text","text":" does not store"},{"type":"text","text":" "},{"type":"text","text":"time information; it represents a day."}]},{"type":"paragraph","inlineContent":[{"type":"text","text":"The "},{"type":"codeVoice","code":"GDate"},{"type":"text","text":" implementation has several nice features; it is only a"},{"type":"text","text":" "},{"type":"text","text":"64-bit struct, so storing large numbers of dates is very efficient. It"},{"type":"text","text":" "},{"type":"text","text":"can keep both a Julian and day-month-year representation of the date,"},{"type":"text","text":" "},{"type":"text","text":"since some calculations are much easier with one representation or the"},{"type":"text","text":" "},{"type":"text","text":"other. A Julian representation is simply a count of days since some"},{"type":"text","text":" "},{"type":"text","text":"fixed day in the past; for "},{"type":"reference","isActive":true,"identifier":"doc:\/\/GLib\/documentation\/GLib\/Date"},{"type":"text","text":" the fixed day is January 1, 1 AD."},{"type":"text","text":" "},{"type":"text","text":"(“Julian” dates in the "},{"type":"reference","isActive":true,"identifier":"doc:\/\/GLib\/documentation\/GLib\/Date"},{"type":"text","text":" API aren’t really Julian dates in the"},{"type":"text","text":" "},{"type":"text","text":"technical sense; technically, Julian dates count from the start of the"},{"type":"text","text":" "},{"type":"text","text":"Julian period, Jan 1, 4713 BC)."}]},{"type":"paragraph","inlineContent":[{"type":"codeVoice","code":"GDate"},{"type":"text","text":" is simple to use. First you need a “blank” date; you can get a"},{"type":"text","text":" "},{"type":"text","text":"dynamically allocated date from [ctor"},{"type":"codeVoice","code":"GLib.Date.new"},{"type":"text","text":"], or you can declare an"},{"type":"text","text":" "},{"type":"text","text":"automatic variable or array and initialize it by calling [method"},{"type":"codeVoice","code":"GLib.Date.clear"},{"type":"text","text":"]."},{"type":"text","text":" "},{"type":"text","text":"A cleared date is safe; it’s safe to call [method"},{"type":"codeVoice","code":"GLib.Date.set_dmy"},{"type":"text","text":"] and the other"},{"type":"text","text":" "},{"type":"text","text":"mutator functions to initialize the value of a cleared date. However, a cleared date"},{"type":"text","text":" "},{"type":"text","text":"is initially invalid, meaning that it doesn’t represent a day that exists."},{"type":"text","text":" "},{"type":"text","text":"It is undefined to call any of the date calculation routines on an invalid date."},{"type":"text","text":" "},{"type":"text","text":"If you obtain a date from a user or other unpredictable source, you should check"},{"type":"text","text":" "},{"type":"text","text":"its validity with the [method"},{"type":"codeVoice","code":"GLib.Date.valid"},{"type":"text","text":"] predicate. [method"},{"type":"codeVoice","code":"GLib.Date.valid"},{"type":"text","text":"]"},{"type":"text","text":" "},{"type":"text","text":"is also used to check for errors with [method"},{"type":"codeVoice","code":"GLib.Date.set_parse"},{"type":"text","text":"] and other functions"},{"type":"text","text":" "},{"type":"text","text":"that can fail. Dates can be invalidated by calling [method"},{"type":"codeVoice","code":"GLib.Date.clear"},{"type":"text","text":"] again."}]},{"type":"paragraph","inlineContent":[{"type":"text","text":"It is very important to use the API to access the "},{"type":"codeVoice","code":"GDate"},{"type":"text","text":" struct. Often only the"},{"type":"text","text":" "},{"type":"text","text":"day-month-year or only the Julian representation is valid. Sometimes neither is valid."},{"type":"text","text":" "},{"type":"text","text":"Use the API."}]},{"type":"paragraph","inlineContent":[{"type":"text","text":"GLib also features "},{"type":"codeVoice","code":"GDateTime"},{"type":"text","text":" which represents a precise time."}]},{"type":"paragraph","inlineContent":[{"type":"text","text":"The "},{"type":"reference","isActive":true,"identifier":"doc:\/\/GLib\/documentation\/GLib\/DateRef"},{"type":"text","text":" type acts as a lightweight Swift reference to an underlying "},{"type":"codeVoice","code":"GDate"},{"type":"text","text":" instance."},{"type":"text","text":" "},{"type":"text","text":"It exposes methods that can operate on this data type through "},{"type":"reference","isActive":true,"identifier":"doc:\/\/GLib\/documentation\/GLib\/DateProtocol"},{"type":"text","text":" conformance."},{"type":"text","text":" "},{"type":"text","text":"Use "},{"type":"reference","isActive":true,"identifier":"doc:\/\/GLib\/documentation\/GLib\/DateRef"},{"type":"text","text":" only as an "},{"type":"codeVoice","code":"unowned"},{"type":"text","text":" reference to an existing "},{"type":"codeVoice","code":"GDate"},{"type":"text","text":" instance."}]},{"style":"note","content":[{"type":"paragraph","inlineContent":[{"type":"text","text":"Use "},{"type":"reference","isActive":true,"identifier":"doc:\/\/GLib\/documentation\/GLib\/Date"},{"type":"text","text":" (instead of "},{"type":"reference","isActive":true,"identifier":"doc:\/\/GLib\/documentation\/GLib\/DateRef"},{"type":"text","text":") if you want to use Automatic Reference Counting for memory management of the underlying "},{"type":"codeVoice","code":"GDate"},{"type":"text","text":" instance."}]}],"type":"aside","name":"Note"}]}],"schemaVersion":{"major":0,"minor":3,"patch":0},"sections":[],"variants":[{"paths":["\/documentation\/glib\/dateref"],"traits":[{"interfaceLanguage":"swift"}]}],"relationshipsSections":[{"identifiers":["doc:\/\/GLib\/documentation\/GLib\/DateProtocol","doc:\/\/GLib\/documentation\/GLib\/PointerWrapper"],"kind":"relationships","title":"Conforms To","type":"conformsTo"}],"identifier":{"url":"doc:\/\/GLib\/documentation\/GLib\/DateRef","interfaceLanguage":"swift"},"abstract":[{"type":"codeVoice","code":"GDate"},{"type":"text","text":" is a struct for calendrical calculations."}],"kind":"symbol","metadata":{"fragments":[{"kind":"keyword","text":"struct"},{"kind":"text","text":" "},{"kind":"identifier","text":"DateRef"}],"title":"DateRef","roleHeading":"Structure","role":"symbol","symbolKind":"struct","externalID":"s:4GLib7DateRefV","modules":[{"name":"GLib"}],"navigatorTitle":[{"kind":"identifier","text":"DateRef"}]},"hierarchy":{"paths":[["doc:\/\/GLib\/documentation\/GLib"]]},"topicSections":[{"title":"Initializers","identifiers":["doc:\/\/GLib\/documentation\/GLib\/DateRef\/init()","doc:\/\/GLib\/documentation\/GLib\/DateRef\/init(_:)-15l2w","doc:\/\/GLib\/documentation\/GLib\/DateRef\/init(_:)-5vh9g","doc:\/\/GLib\/documentation\/GLib\/DateRef\/init(_:)-6v7fp","doc:\/\/GLib\/documentation\/GLib\/DateRef\/init(_:)-7pk3a","doc:\/\/GLib\/documentation\/GLib\/DateRef\/init(_:)-9375e","doc:\/\/GLib\/documentation\/GLib\/DateRef\/init(cPointer:)","doc:\/\/GLib\/documentation\/GLib\/DateRef\/init(constPointer:)","doc:\/\/GLib\/documentation\/GLib\/DateRef\/init(dmy:month:year:)","doc:\/\/GLib\/documentation\/GLib\/DateRef\/init(gconstpointer:)","doc:\/\/GLib\/documentation\/GLib\/DateRef\/init(gpointer:)","doc:\/\/GLib\/documentation\/GLib\/DateRef\/init(julian:)","doc:\/\/GLib\/documentation\/GLib\/DateRef\/init(mutating:)","doc:\/\/GLib\/documentation\/GLib\/DateRef\/init(opaquePointer:)"]},{"title":"Instance Properties","identifiers":["doc:\/\/GLib\/documentation\/GLib\/DateRef\/ptr"]},{"title":"Type Methods","identifiers":["doc:\/\/GLib\/documentation\/GLib\/DateRef\/new(dmy:month:year:)","doc:\/\/GLib\/documentation\/GLib\/DateRef\/new(julian:)"]},{"title":"Default Implementations","identifiers":["doc:\/\/GLib\/documentation\/GLib\/DateRef\/DateProtocol-Implementations","doc:\/\/GLib\/documentation\/GLib\/DateRef\/PointerWrapper-Implementations"],"generated":true}],"references":{"doc://GLib/documentation/GLib/DateRef/init(_:)-6v7fp":{"role":"symbol","title":"init(_:)","fragments":[{"kind":"identifier","text":"init"},{"kind":"text","text":"!("},{"kind":"typeIdentifier","text":"UnsafePointer","preciseIdentifier":"s:SP"},{"kind":"text","text":"<"},{"kind":"typeIdentifier","text":"GDate"},{"kind":"text","text":">?)"}],"abstract":[{"type":"text","text":"Conditional initialiser from an optional, non-mutable pointer to the underlying "},{"type":"codeVoice","code":"C"},{"type":"text","text":" data type"}],"identifier":"doc:\/\/GLib\/documentation\/GLib\/DateRef\/init(_:)-6v7fp","kind":"symbol","type":"topic","url":"\/documentation\/glib\/dateref\/init(_:)-6v7fp"},"doc://GLib/documentation/GLib/DateRef/init(mutating:)":{"role":"symbol","title":"init(mutating:)","fragments":[{"kind":"identifier","text":"init"},{"kind":"text","text":"("},{"kind":"externalParam","text":"mutating"},{"kind":"text","text":": "},{"kind":"typeIdentifier","text":"UnsafeRawPointer","preciseIdentifier":"s:SV"},{"kind":"text","text":")"}],"abstract":[{"type":"text","text":"Unsafe untyped initialiser."},{"type":"text","text":" "},{"type":"strong","inlineContent":[{"type":"text","text":"Do not use unless you know the underlying data type the pointer points to conforms to "},{"type":"reference","isActive":true,"identifier":"doc:\/\/GLib\/documentation\/GLib\/DateProtocol"},{"type":"text","text":"."}]}],"identifier":"doc:\/\/GLib\/documentation\/GLib\/DateRef\/init(mutating:)","kind":"symbol","type":"topic","url":"\/documentation\/glib\/dateref\/init(mutating:)"},"doc://GLib/documentation/GLib/DateProtocol":{"role":"symbol","title":"DateProtocol","fragments":[{"kind":"keyword","text":"protocol"},{"kind":"text","text":" "},{"kind":"identifier","text":"DateProtocol"}],"abstract":[{"type":"codeVoice","code":"GDate"},{"type":"text","text":" is a struct for calendrical calculations."}],"identifier":"doc:\/\/GLib\/documentation\/GLib\/DateProtocol","kind":"symbol","type":"topic","navigatorTitle":[{"kind":"identifier","text":"DateProtocol"}],"url":"\/documentation\/glib\/dateprotocol"},"doc://GLib/documentation/GLib/DateRef/init(_:)-15l2w":{"role":"symbol","title":"init(_:)","fragments":[{"kind":"identifier","text":"init"},{"kind":"text","text":"<"},{"kind":"genericParameter","text":"T"},{"kind":"text","text":">("},{"kind":"typeIdentifier","text":"T"},{"kind":"text","text":")"}],"abstract":[{"type":"text","text":"Reference intialiser for a related type that implements "},{"type":"reference","isActive":true,"identifier":"doc:\/\/GLib\/documentation\/GLib\/DateProtocol"}],"identifier":"doc:\/\/GLib\/documentation\/GLib\/DateRef\/init(_:)-15l2w","kind":"symbol","type":"topic","url":"\/documentation\/glib\/dateref\/init(_:)-15l2w"},"doc://GLib/documentation/GLib/DateRef/init(dmy:month:year:)":{"role":"symbol","title":"init(dmy:month:year:)","fragments":[{"kind":"identifier","text":"init"},{"kind":"text","text":"("},{"kind":"externalParam","text":"dmy"},{"kind":"text","text":": "},{"kind":"typeIdentifier","text":"GDateDay","preciseIdentifier":"c:@T@GDateDay"},{"kind":"text","text":", "},{"kind":"externalParam","text":"month"},{"kind":"text","text":": "},{"kind":"typeIdentifier","text":"GDateMonth","preciseIdentifier":"c:@EA@GDateMonth"},{"kind":"text","text":", "},{"kind":"externalParam","text":"year"},{"kind":"text","text":": "},{"kind":"typeIdentifier","text":"GDateYear","preciseIdentifier":"c:@T@GDateYear"},{"kind":"text","text":")"}],"abstract":[{"type":"text","text":"Create a new "},{"type":"reference","isActive":true,"identifier":"doc:\/\/GLib\/documentation\/GLib\/Date"},{"type":"text","text":" representing the given day-month-year triplet."}],"identifier":"doc:\/\/GLib\/documentation\/GLib\/DateRef\/init(dmy:month:year:)","kind":"symbol","type":"topic","url":"\/documentation\/glib\/dateref\/init(dmy:month:year:)"},"doc://GLib/documentation/GLib/DateProtocol/date_ptr-9p0th":{"defaultImplementations":1,"role":"symbol","title":"date_ptr","fragments":[{"kind":"keyword","text":"var"},{"kind":"text","text":" "},{"kind":"identifier","text":"date_ptr"},{"kind":"text","text":": "},{"kind":"typeIdentifier","text":"UnsafeMutablePointer","preciseIdentifier":"s:Sp"},{"kind":"text","text":"<"},{"kind":"typeIdentifier","text":"GDate"},{"kind":"text","text":">!"}],"abstract":[{"type":"text","text":"Typed pointer to the underlying "},{"type":"codeVoice","code":"GDate"},{"type":"text","text":" instance."}],"identifier":"doc:\/\/GLib\/documentation\/GLib\/DateProtocol\/date_ptr-9p0th","kind":"symbol","required":true,"type":"topic","url":"\/documentation\/glib\/dateprotocol\/date_ptr-9p0th"},"doc://GLib/documentation/GLib/Date":{"role":"symbol","title":"Date","fragments":[{"kind":"keyword","text":"class"},{"kind":"text","text":" "},{"kind":"identifier","text":"Date"}],"abstract":[{"type":"codeVoice","code":"GDate"},{"type":"text","text":" is a struct for calendrical calculations."}],"identifier":"doc:\/\/GLib\/documentation\/GLib\/Date","kind":"symbol","type":"topic","navigatorTitle":[{"kind":"identifier","text":"Date"}],"url":"\/documentation\/glib\/date"},"doc://GLib/documentation/GLib/DateRef/init(_:)-9375e":{"role":"symbol","title":"init(_:)","fragments":[{"kind":"identifier","text":"init"},{"kind":"text","text":"("},{"kind":"typeIdentifier","text":"UnsafePointer","preciseIdentifier":"s:SP"},{"kind":"text","text":"<"},{"kind":"typeIdentifier","text":"GDate"},{"kind":"text","text":">)"}],"abstract":[{"type":"text","text":"Designated initialiser from a constant pointer to the underlying "},{"type":"codeVoice","code":"C"},{"type":"text","text":" data type"}],"identifier":"doc:\/\/GLib\/documentation\/GLib\/DateRef\/init(_:)-9375e","kind":"symbol","type":"topic","url":"\/documentation\/glib\/dateref\/init(_:)-9375e"},"doc://GLib/documentation/GLib/DateRef/new(dmy:month:year:)":{"role":"symbol","title":"new(dmy:month:year:)","fragments":[{"kind":"keyword","text":"static"},{"kind":"text","text":" "},{"kind":"keyword","text":"func"},{"kind":"text","text":" "},{"kind":"identifier","text":"new"},{"kind":"text","text":"("},{"kind":"externalParam","text":"dmy"},{"kind":"text","text":": "},{"kind":"typeIdentifier","text":"GDateDay","preciseIdentifier":"c:@T@GDateDay"},{"kind":"text","text":", "},{"kind":"externalParam","text":"month"},{"kind":"text","text":": "},{"kind":"typeIdentifier","text":"GDateMonth","preciseIdentifier":"c:@EA@GDateMonth"},{"kind":"text","text":", "},{"kind":"externalParam","text":"year"},{"kind":"text","text":": "},{"kind":"typeIdentifier","text":"GDateYear","preciseIdentifier":"c:@T@GDateYear"},{"kind":"text","text":") -> "},{"kind":"typeIdentifier","text":"DateRef","preciseIdentifier":"s:4GLib7DateRefV"},{"kind":"text","text":"!"}],"abstract":[{"type":"text","text":"Create a new "},{"type":"reference","isActive":true,"identifier":"doc:\/\/GLib\/documentation\/GLib\/Date"},{"type":"text","text":" representing the given day-month-year triplet."}],"identifier":"doc:\/\/GLib\/documentation\/GLib\/DateRef\/new(dmy:month:year:)","kind":"symbol","type":"topic","url":"\/documentation\/glib\/dateref\/new(dmy:month:year:)"},"doc://GLib/documentation/GLib/DateRef/init(opaquePointer:)":{"role":"symbol","title":"init(opaquePointer:)","fragments":[{"kind":"identifier","text":"init"},{"kind":"text","text":"("},{"kind":"externalParam","text":"opaquePointer"},{"kind":"text","text":": "},{"kind":"typeIdentifier","text":"OpaquePointer","preciseIdentifier":"s:s13OpaquePointerV"},{"kind":"text","text":")"}],"abstract":[{"type":"text","text":"Unsafe untyped initialiser."},{"type":"text","text":" "},{"type":"strong","inlineContent":[{"type":"text","text":"Do not use unless you know the underlying data type the pointer points to conforms to "},{"type":"reference","isActive":true,"identifier":"doc:\/\/GLib\/documentation\/GLib\/DateProtocol"},{"type":"text","text":"."}]}],"identifier":"doc:\/\/GLib\/documentation\/GLib\/DateRef\/init(opaquePointer:)","kind":"symbol","type":"topic","url":"\/documentation\/glib\/dateref\/init(opaquepointer:)"},"doc://GLib/documentation/GLib/DateRef/init(constPointer:)":{"role":"symbol","title":"init(constPointer:)","fragments":[{"kind":"identifier","text":"init"},{"kind":"text","text":"<"},{"kind":"genericParameter","text":"T"},{"kind":"text","text":">("},{"kind":"externalParam","text":"constPointer"},{"kind":"text","text":": "},{"kind":"typeIdentifier","text":"UnsafePointer","preciseIdentifier":"s:SP"},{"kind":"text","text":"<"},{"kind":"typeIdentifier","text":"T"},{"kind":"text","text":">)"}],"abstract":[{"type":"text","text":"Unsafe typed initialiser."},{"type":"text","text":" "},{"type":"strong","inlineContent":[{"type":"text","text":"Do not use unless you know the underlying data type the pointer points to conforms to "},{"type":"reference","isActive":true,"identifier":"doc:\/\/GLib\/documentation\/GLib\/DateProtocol"},{"type":"text","text":"."}]}],"identifier":"doc:\/\/GLib\/documentation\/GLib\/DateRef\/init(constPointer:)","kind":"symbol","type":"topic","url":"\/documentation\/glib\/dateref\/init(constpointer:)"},"doc://GLib/documentation/GLib/DateRef":{"role":"symbol","title":"DateRef","fragments":[{"kind":"keyword","text":"struct"},{"kind":"text","text":" "},{"kind":"identifier","text":"DateRef"}],"abstract":[{"type":"codeVoice","code":"GDate"},{"type":"text","text":" is a struct for calendrical calculations."}],"identifier":"doc:\/\/GLib\/documentation\/GLib\/DateRef","kind":"symbol","type":"topic","navigatorTitle":[{"kind":"identifier","text":"DateRef"}],"url":"\/documentation\/glib\/dateref"},"doc://GLib/documentation/GLib/DateRef/init(_:)-7pk3a":{"role":"symbol","title":"init(_:)","fragments":[{"kind":"identifier","text":"init"},{"kind":"text","text":"("},{"kind":"typeIdentifier","text":"UnsafeMutablePointer","preciseIdentifier":"s:Sp"},{"kind":"text","text":"<"},{"kind":"typeIdentifier","text":"GDate"},{"kind":"text","text":">)"}],"abstract":[{"type":"text","text":"Designated initialiser from the underlying "},{"type":"codeVoice","code":"C"},{"type":"text","text":" data type"}],"identifier":"doc:\/\/GLib\/documentation\/GLib\/DateRef\/init(_:)-7pk3a","kind":"symbol","type":"topic","url":"\/documentation\/glib\/dateref\/init(_:)-7pk3a"},"doc://GLib/documentation/GLib/DateRef/init(julian:)":{"role":"symbol","title":"init(julian:)","fragments":[{"kind":"identifier","text":"init"},{"kind":"text","text":"("},{"kind":"externalParam","text":"julian"},{"kind":"text","text":": "},{"kind":"typeIdentifier","text":"guint32","preciseIdentifier":"c:@T@guint32"},{"kind":"text","text":")"}],"abstract":[{"type":"text","text":"Create a new "},{"type":"reference","isActive":true,"identifier":"doc:\/\/GLib\/documentation\/GLib\/Date"},{"type":"text","text":" representing the given Julian date."}],"identifier":"doc:\/\/GLib\/documentation\/GLib\/DateRef\/init(julian:)","kind":"symbol","type":"topic","url":"\/documentation\/glib\/dateref\/init(julian:)"},"doc://GLib/documentation/GLib/DateRef/init(_:)-5vh9g":{"role":"symbol","title":"init(_:)","fragments":[{"kind":"identifier","text":"init"},{"kind":"text","text":"!("},{"kind":"typeIdentifier","text":"UnsafeMutablePointer","preciseIdentifier":"s:Sp"},{"kind":"text","text":"<"},{"kind":"typeIdentifier","text":"GDate"},{"kind":"text","text":">?)"}],"abstract":[{"type":"text","text":"Conditional initialiser from an optional pointer to the underlying "},{"type":"codeVoice","code":"C"},{"type":"text","text":" data type"}],"identifier":"doc:\/\/GLib\/documentation\/GLib\/DateRef\/init(_:)-5vh9g","kind":"symbol","type":"topic","url":"\/documentation\/glib\/dateref\/init(_:)-5vh9g"},"doc://GLib/documentation/GLib/DateRef/init(gconstpointer:)":{"role":"symbol","title":"init(gconstpointer:)","fragments":[{"kind":"identifier","text":"init"},{"kind":"text","text":"!("},{"kind":"externalParam","text":"gconstpointer"},{"kind":"text","text":": "},{"kind":"typeIdentifier","text":"gconstpointer","preciseIdentifier":"c:@T@gconstpointer"},{"kind":"text","text":"?)"}],"abstract":[{"type":"text","text":"Conditional initialiser from an optional, non-mutable "},{"type":"codeVoice","code":"gconstpointer"}],"identifier":"doc:\/\/GLib\/documentation\/GLib\/DateRef\/init(gconstpointer:)","kind":"symbol","type":"topic","url":"\/documentation\/glib\/dateref\/init(gconstpointer:)"},"doc://GLib/documentation/GLib/DateRef/DateProtocol-Implementations":{"role":"collectionGroup","title":"DateProtocol Implementations","abstract":[],"identifier":"doc:\/\/GLib\/documentation\/GLib\/DateRef\/DateProtocol-Implementations","kind":"article","type":"topic","url":"\/documentation\/glib\/dateref\/dateprotocol-implementations"},"doc://GLib/documentation/GLib/DateRef/init(cPointer:)":{"role":"symbol","title":"init(cPointer:)","fragments":[{"kind":"identifier","text":"init"},{"kind":"text","text":"<"},{"kind":"genericParameter","text":"T"},{"kind":"text","text":">("},{"kind":"externalParam","text":"cPointer"},{"kind":"text","text":": "},{"kind":"typeIdentifier","text":"UnsafeMutablePointer","preciseIdentifier":"s:Sp"},{"kind":"text","text":"<"},{"kind":"typeIdentifier","text":"T"},{"kind":"text","text":">)"}],"abstract":[{"type":"text","text":"Unsafe typed initialiser."},{"type":"text","text":" "},{"type":"strong","inlineContent":[{"type":"text","text":"Do not use unless you know the underlying data type the pointer points to conforms to "},{"type":"reference","isActive":true,"identifier":"doc:\/\/GLib\/documentation\/GLib\/DateProtocol"},{"type":"text","text":"."}]}],"identifier":"doc:\/\/GLib\/documentation\/GLib\/DateRef\/init(cPointer:)","kind":"symbol","type":"topic","url":"\/documentation\/glib\/dateref\/init(cpointer:)"},"doc://GLib/documentation/GLib/DateRef/ptr":{"role":"symbol","title":"ptr","fragments":[{"kind":"keyword","text":"let"},{"kind":"text","text":" "},{"kind":"identifier","text":"ptr"},{"kind":"text","text":": "},{"kind":"typeIdentifier","text":"UnsafeMutableRawPointer","preciseIdentifier":"s:Sv"},{"kind":"text","text":"!"}],"abstract":[{"type":"text","text":"Untyped pointer to the underlying "},{"type":"codeVoice","code":"GDate"},{"type":"text","text":" instance."},{"type":"text","text":" "},{"type":"text","text":"For type-safe access, use the generated, typed pointer "},{"type":"reference","isActive":true,"identifier":"doc:\/\/GLib\/documentation\/GLib\/DateProtocol\/date_ptr-9p0th"},{"type":"text","text":" property instead."}],"identifier":"doc:\/\/GLib\/documentation\/GLib\/DateRef\/ptr","kind":"symbol","type":"topic","url":"\/documentation\/glib\/dateref\/ptr"},"doc://GLib/documentation/GLib/PointerWrapper":{"role":"symbol","title":"PointerWrapper","fragments":[{"kind":"keyword","text":"protocol"},{"kind":"text","text":" "},{"kind":"identifier","text":"PointerWrapper"}],"abstract":[{"type":"text","text":"Protocol for GLib types that wrap pointers."}],"identifier":"doc:\/\/GLib\/documentation\/GLib\/PointerWrapper","kind":"symbol","type":"topic","navigatorTitle":[{"kind":"identifier","text":"PointerWrapper"}],"url":"\/documentation\/glib\/pointerwrapper"},"doc://GLib/documentation/GLib/DateRef/init()":{"role":"symbol","title":"init()","fragments":[{"kind":"identifier","text":"init"},{"kind":"text","text":"()"}],"abstract":[{"type":"text","text":"Allocates a "},{"type":"reference","isActive":true,"identifier":"doc:\/\/GLib\/documentation\/GLib\/Date"},{"type":"text","text":" and initializes"},{"type":"text","text":" "},{"type":"text","text":"it to a safe state. The new date will"},{"type":"text","text":" "},{"type":"text","text":"be cleared (as if you’d called "},{"type":"codeVoice","code":"g_date_clear()"},{"type":"text","text":") but invalid (it won’t"},{"type":"text","text":" "},{"type":"text","text":"represent an existing day). Free the return value with "},{"type":"codeVoice","code":"g_date_free()"},{"type":"text","text":"."}],"identifier":"doc:\/\/GLib\/documentation\/GLib\/DateRef\/init()","kind":"symbol","type":"topic","url":"\/documentation\/glib\/dateref\/init()"},"doc://GLib/documentation/GLib/DateRef/PointerWrapper-Implementations":{"role":"collectionGroup","title":"PointerWrapper Implementations","abstract":[],"identifier":"doc:\/\/GLib\/documentation\/GLib\/DateRef\/PointerWrapper-Implementations","kind":"article","type":"topic","url":"\/documentation\/glib\/dateref\/pointerwrapper-implementations"},"doc://GLib/documentation/GLib/DateRef/new(julian:)":{"role":"symbol","title":"new(julian:)","fragments":[{"kind":"keyword","text":"static"},{"kind":"text","text":" "},{"kind":"keyword","text":"func"},{"kind":"text","text":" "},{"kind":"identifier","text":"new"},{"kind":"text","text":"("},{"kind":"externalParam","text":"julian"},{"kind":"text","text":": "},{"kind":"typeIdentifier","text":"guint32","preciseIdentifier":"c:@T@guint32"},{"kind":"text","text":") -> "},{"kind":"typeIdentifier","text":"DateRef","preciseIdentifier":"s:4GLib7DateRefV"},{"kind":"text","text":"!"}],"abstract":[{"type":"text","text":"Create a new "},{"type":"reference","isActive":true,"identifier":"doc:\/\/GLib\/documentation\/GLib\/Date"},{"type":"text","text":" representing the given Julian date."}],"identifier":"doc:\/\/GLib\/documentation\/GLib\/DateRef\/new(julian:)","kind":"symbol","type":"topic","url":"\/documentation\/glib\/dateref\/new(julian:)"},"doc://GLib/documentation/GLib":{"role":"collection","title":"GLib","abstract":[],"identifier":"doc:\/\/GLib\/documentation\/GLib","kind":"symbol","type":"topic","url":"\/documentation\/glib"},"doc://GLib/documentation/GLib/DateRef/init(gpointer:)":{"role":"symbol","title":"init(gpointer:)","fragments":[{"kind":"identifier","text":"init"},{"kind":"text","text":"!("},{"kind":"externalParam","text":"gpointer"},{"kind":"text","text":": "},{"kind":"typeIdentifier","text":"gpointer","preciseIdentifier":"c:@T@gpointer"},{"kind":"text","text":"?)"}],"abstract":[{"type":"text","text":"Conditional initialiser from an optional "},{"type":"codeVoice","code":"gpointer"}],"identifier":"doc:\/\/GLib\/documentation\/GLib\/DateRef\/init(gpointer:)","kind":"symbol","type":"topic","url":"\/documentation\/glib\/dateref\/init(gpointer:)"}}}